to_test/i2s/v2/i2s_pmod_v2.v
`default_nettype none

/* The default is 25mhz as input clk
  we are going to target mclk= 12.28mhz, lrck=96khz, ie x128 in the 
  chart https://reference.digilentinc.com/reference/pmod/pmodi2s2/reference-manual
  for that mclk=clk_in/2; lrck=clk_in/256 and sclk=clk_in/4
  (I would think that you could modify the parameters to get the i2s pmod 
  work in other configuration, but I havent test it)

  The i2s protocol present the data in the data in the falling edge of sclk.
  The data is in 2 complement and the msb is presented first.
  The change of the lrck occurs in the lsb of the previous word. 

  Is recommended to use a oddr at the output clocks (Some people argue 
  that driving the clock without oddr gives you a bad routing in the clock
  tree).
*/

module i2s_pmod_v2 #(
    parameter CLK_FREQ = 25_000_000,
    parameter MCLK_DEC = 1,         //2**MCLK_DEC decimation factor of mclk
    parameter LRCK_DEC = 8,         //2**LRCK_DEC decimation factor of lrck
    parameter SCLK_DEC = 2          //2**SCLK_DEC decimation factor of sclk
) (
    input wire clk,
    
    //adc fpga interfaces
    //valid 0:right, 1:left
    output wire [31:0] adc_r_tdata,
    output wire [31:0] adc_l_tdata,
    output wire [1:0]  adc_tvalid,
    input  wire [1:0]  adc_tready,

    //dac fpga interfaces
    //valid 0:rigth, 1:left
    input  wire [31:0] dac_r_tdata,
    input  wire [31:0] dac_l_tdata,
    input  wire [1:0]  dac_tvalid,
    output wire [1:0]  dac_tready,

    //physical interfaces
    output wire dac_mclk,
    output wire dac_lrck,
    output wire dac_sclk,
    output wire dac_sdat,

    output wire adc_mclk,
    output wire adc_lrck,
    output wire adc_sclk,
    input  wire adc_dat 
);

reg [LRCK_DEC:0] counter=0; //counter has one more bit to count
                            //l and r with the same counter;
always@(posedge clk)begin
    counter <= counter+1;
end

//clock assignations
assign dac_mclk = counter[MCLK_DEC-1];
assign dac_lrck = counter[LRCK_DEC-1];
assign dac_sclk = counter[SCLK_DEC-1];

assign adc_mclk = counter[MCLK_DEC-1];
assign adc_lrck = counter[LRCK_DEC-1];
assign adc_sclk = counter[SCLK_DEC-1];

//delay in the lrck to detect the edges
reg lrck_dly=1'b0;
always@(posedge clk)begin
    lrck_dly <= adc_lrck;
end


//dac axi stream handshakes
reg [1:0] dac_tready_r = 2'b11;
assign dac_tready = dac_tready_r;
reg [63:0] dac_r_shift=0, dac_l_shift=0;

always@(posedge clk)begin
    if(dac_tvalid && |dac_tready_r)begin
        if(dac_tready_r[0])begin
            dac_r_shift[31:0] <= dac_r_tdata;
            dac_tready_r[0] <= 1'b0;
        end
        if(dac_tready_r[1])begin
            dac_l_shift[31:0] <= dac_l_tdata;
            dac_tready_r[1] <= 1'b0;
        end
    end
    else if(~adc_lrck && lrck_dly)begin
        //falling edge, ie end of rigth channel frame
        dac_tready_r[0] <= 1'b1;
        dac_r_shift <= {dac_r_shift[31:0], 32'b0};
    end    
    else if(adc_lrck && ~lrck_dly)begin
        //rising edge, ie end of left channel frame
        dac_tready_r[1]<= 1'b1;
        dac_l_shift <= {dac_l_shift[31:0], 32'b0};
    end
    else begin
        dac_tready_r <= dac_tready;
        dac_l_shift <= dac_l_shift;
        dac_r_shift <= dac_r_shift;
    end
end

//shift the data out
//we have to update the data in the falling edge of the sclk so
//thats when &counter[SCLK_DEC-1:0], also the index of the data 
//would be given by counter[SCLK_DEC+:5] 
reg dac_out=0;
assign dac_sdat = dac_out;
wire [5:0] index;
assign index = 63-counter[SCLK_DEC+:5];
wire sdat_update;
assign sdat_update= &counter[SCLK_DEC-1:0];

always@(posedge clk)begin
    if(sdat_update)begin
        if(dac_lrck)
            dac_out <= dac_l_shift[index];
        else
            dac_out <= dac_r_shift[index];
    end
    else
        dac_out <= dac_out;
end

//the dac part seems to be working as expected

//adc part
//synchronizer
//first we need to delay one sclk cycle lrck(to match the lsb)
reg [SCLK_DEC-1:0] lrck_dly_2=0;
always@(posedge clk)begin
    lrck_dly_2 <= {lrck_dly_2[SCLK_DEC-2:0], adc_lrck};
end



reg [2:0] sync_adc_dat = 3'b0, adc_sclk_dly = 3'b0, adc_lrck_dly=3'b0;
always@(posedge clk)begin
    sync_adc_dat <= {sync_adc_dat[1:0], adc_dat};
    adc_sclk_dly <= {adc_sclk_dly[1:0], adc_sclk};
    adc_lrck_dly <= {adc_lrck_dly[1:0], lrck_dly_2[SCLK_DEC-1]};
end

//in this case we have to sample in the rising edge of the sclk
//because in that part the data is stable

reg [63:0] adc_l_shift=0, adc_r_shift=0;
always@(posedge clk)begin
    if(~adc_sclk_dly[2]&&adc_sclk_dly[1])begin
        if(adc_lrck_dly[2])
            adc_r_shift <= {adc_r_shift[62:0], sync_adc_dat[2]};
        else
            adc_l_shift <= {adc_l_shift[62:0], sync_adc_dat[2]};
    end
    else begin
        adc_r_shift <= adc_r_shift;
        adc_l_shift <= adc_l_shift;
    end
end

//axi handshake
//the data is valid when we are sapmling the msb of the next frame
reg [1:0] adc_tvalid_r = 2'b0;
assign adc_tvalid = adc_tvalid_r;
reg [31:0] adc_r_tdata_r=0, adc_l_tdata_r=0;
assign adc_r_tdata = adc_r_tdata_r;
assign adc_l_tdata = adc_l_tdata_r;

always@(posedge clk)begin
    if(adc_lrck_dly[2]&& ~adc_lrck_dly[1])begin
        //rising edge, the left channel is ready
        adc_l_tdata_r <= adc_l_shift[63:32];
        adc_tvalid_r[1] <= 1'b1;
    end
    else if(~adc_lrck_dly[2] && adc_lrck_dly[1])begin
        //falling edge, the right channel is ready
        adc_r_tdata_r <= adc_r_shift[63:32];
        adc_tvalid_r[0] <= 1'b1;
    end
    else begin
        adc_r_tdata_r <= adc_r_tdata_r;
        adc_l_tdata_r <= adc_l_tdata_r;
        if(adc_tvalid[0]&&adc_tready[0])
            adc_tvalid_r[0] <= 1'b0;
        if(adc_tvalid[1]&&adc_tready[1])
            adc_tvalid_r[1] <= 1'b0;
    end
end





endmodule

to_test/i2s/v2/i2s_pmod_tb.v
`default_nettype none
`include "i2s_pmod_v2.v"

module i2s_pmod_tb #(
    parameter CLK_FREQ = 25_000_000,
    parameter MCLK_DEC = 1,         //2**MCLK_DEC decimation factor of mclk
    parameter LRCK_DEC = 8,         //2**LRCK_DEC decimation factor of lrck
    parameter SCLK_DEC = 2          //2**SCLK_DEC decimation factor of sclk
) (
    input wire clk,
    
    //adc fpga interfaces
    //valid 0:right, 1:left
    output wire [31:0] adc_r_tdata,
    output wire [31:0] adc_l_tdata,
    output wire [1:0]  adc_tvalid,
    input  wire [1:0]  adc_tready,

    //dac fpga interfaces
    //valid 0:rigth, 1:left
    input  wire [31:0] dac_r_tdata,
    input  wire [31:0] dac_l_tdata,
    input  wire [1:0]  dac_tvalid,
    output wire [1:0]  dac_tready,

    //physical interfaces
    output wire dac_mclk,
    output wire dac_lrck,
    output wire dac_sclk,
    output wire dac_sdat,

    output wire adc_mclk,
    output wire adc_lrck,
    output wire adc_sclk,
    input  wire adc_dat 
);

i2s_pmod_v2 #(
    .CLK_FREQ(CLK_FREQ),
    .MCLK_DEC(MCLK_DEC),
    .LRCK_DEC(LRCK_DEC),
    .SCLK_DEC(SCLK_DEC)
) i2s_pmod_inst (
    .clk(clk),
    .adc_r_tdata(adc_r_tdata),
    .adc_l_tdata(adc_l_tdata),
    .adc_tvalid(adc_tvalid),
    .adc_tready(adc_tready),
    .dac_r_tdata(dac_r_tdata),
    .dac_l_tdata(dac_l_tdata),
    .dac_tvalid(dac_tvalid),
    .dac_tready(dac_tready),
    .dac_mclk(dac_mclk),
    .dac_lrck(dac_lrck),
    .dac_sclk(dac_sclk),
    .dac_sdat(dac_sdat),
    .adc_mclk(adc_mclk),
    .adc_lrck(adc_lrck),
    .adc_sclk(adc_sclk),
    .adc_dat(adc_dat)
);

initial begin
    $dumpfile("traces.vcd");
    $dumpvars();
end


endmodule

to_test/i2s/v2/traces.vcd
$date
	Wed Feb 17 16:35:26 2021
$end
$version
	Icarus Verilog
$end
$timescale
	1ps
$end
$scope module i2s_pmod_tb $end
$var wire 1 ! adc_dat $end
$var wire 2 " adc_tready [1:0] $end
$var wire 1 # clk $end
$var wire 32 $ dac_l_tdata [31:0] $end
$var wire 32 % dac_r_tdata [31:0] $end
$var wire 2 & dac_tvalid [1:0] $end
$var wire 2 ' dac_tready [1:0] $end
$var wire 1 ( dac_sdat $end
$var wire 1 ) dac_sclk $end
$var wire 1 * dac_mclk $end
$var wire 1 + dac_lrck $end
$var wire 2 , adc_tvalid [1:0] $end
$var wire 1 - adc_sclk $end
$var wire 32 . adc_r_tdata [31:0] $end
$var wire 1 / adc_mclk $end
$var wire 1 0 adc_lrck $end
$var wire 32 1 adc_l_tdata [31:0] $end
$scope module i2s_pmod_inst $end
$var wire 1 ! adc_dat $end
$var wire 32 2 adc_l_tdata [31:0] $end
$var wire 32 3 adc_r_tdata [31:0] $end
$var wire 2 4 adc_tready [1:0] $end
$var wire 2 5 adc_tvalid [1:0] $end
$var wire 1 # clk $end
$var wire 32 6 dac_l_tdata [31:0] $end
$var wire 32 7 dac_r_tdata [31:0] $end
$var wire 1 ( dac_sdat $end
$var wire 2 8 dac_tready [1:0] $end
$var wire 2 9 dac_tvalid [1:0] $end
$var wire 1 : sdat_update $end
$var wire 6 ; index [5:0] $end
$var wire 1 ) dac_sclk $end
$var wire 1 * dac_mclk $end
$var wire 1 + dac_lrck $end
$var wire 1 - adc_sclk $end
$var wire 1 / adc_mclk $end
$var wire 1 0 adc_lrck $end
$var reg 64 < adc_l_shift [63:0] $end
$var reg 32 = adc_l_tdata_r [31:0] $end
$var reg 3 > adc_lrck_dly [2:0] $end
$var reg 64 ? adc_r_shift [63:0] $end
$var reg 32 @ adc_r_tdata_r [31:0] $end
$var reg 3 A adc_sclk_dly [2:0] $end
$var reg 2 B adc_tvalid_r [1:0] $end
$var reg 9 C counter [8:0] $end
$var reg 64 D dac_l_shift [63:0] $end
$var reg 1 E dac_out $end
$var reg 64 F dac_r_shift [63:0] $end
$var reg 2 G dac_tready_r [1:0] $end
$var reg 1 H lrck_dly $end
$var reg 2 I lrck_dly_2 [1:0] $end
$var reg 3 J sync_adc_dat [2:0] $end
$upscope $end
$upscope $end
$enddefinitions $end
#0
$dumpvars
b0 J
b0 I
0H
b11 G
b0 F
0E
b0 D
b1 C
b0 B
b0 A
b0 @
b0 ?
b0 >
b0 =
b0 <
b111111 ;
0:
bz 9
b11 8
bz 7
bz 6
b0 5
bz 4
b0 3
b0 2
b0 1
00
1/
b0 .
0-
b0 ,
0+
1*
0)
0(
b11 '
bz &
bz %
bz $
1#
bz "
0!
$end
#5000
0#
#10000
b0 "
b0 4
0*
1)
0/
1-
b10 C
1#
#15000
0#
#20000
1*
1/
1:
b11 C
b1 A
1#
#25000
0#
#30000
b111110 ;
0*
0)
0/
0-
0:
b11 A
b100 C
1#
#35000
0#
#40000
1*
1/
b101 C
b110 A
1#
#45000
0#
#50000
0*
1)
0/
1-
b100 A
b110 C
1#
#55000
0#
#60000
1*
1/
1:
b111 C
b1 A
1#
#65000
0#
#70000
b111101 ;
0*
0)
0/
0-
0:
b11 A
b1000 C
1#
#75000
0#
#80000
1*
1/
b1001 C
b110 A
1#
#85000
0#
#90000
0*
1)
0/
1-
b100 A
b1010 C
1#
#95000
0#
#100000
1*
1/
1:
b1011 C
b1 A
1#
#105000
0#
#110000
b111100 ;
0*
0)
0/
0-
0:
b11 A
b1100 C
1#
#115000
0#
#120000
1*
1/
b1101 C
b110 A
1#
#125000
0#
#130000
0*
1)
0/
1-
b100 A
b1110 C
1#
#135000
0#
#140000
1*
1/
1:
b1111 C
b1 A
1#
#145000
0#
#150000
b111011 ;
0*
0)
0/
0-
0:
b11 A
b10000 C
1#
#155000
0#
#160000
1*
1/
b10001 C
b110 A
1#
#165000
0#
#170000
0*
1)
0/
1-
b100 A
b10010 C
1#
#175000
0#
#180000
1*
1/
1:
b10011 C
b1 A
1#
#185000
0#
#190000
b111010 ;
0*
0)
0/
0-
0:
b11 A
b10100 C
1#
#195000
0#
#200000
1*
1/
b10101 C
b110 A
1#
#205000
0#
#210000
0*
1)
0/
1-
b100 A
b10110 C
1#
#215000
0#
#220000
1*
1/
1:
b10111 C
b1 A
1#
#225000
0#
#230000
b111001 ;
0*
0)
0/
0-
0:
b11 A
b11000 C
1#
#235000
0#
#240000
1*
1/
b11001 C
b110 A
1#
#245000
0#
#250000
0*
1)
0/
1-
b100 A
b11010 C
1#
#255000
0#
#260000
1*
1/
1:
b11011 C
b1 A
1#
#265000
0#
#270000
b111000 ;
0*
0)
0/
0-
0:
b11 A
b11100 C
1#
#275000
0#
#280000
1*
1/
b11101 C
b110 A
1#
#285000
0#
#290000
0*
1)
0/
1-
b100 A
b11110 C
1#
#295000
0#
#300000
1*
1/
1:
b11111 C
b1 A
1#
#305000
0#
#310000
b110111 ;
0*
0)
0/
0-
0:
b11 A
b100000 C
1#
#315000
0#
#320000
1*
1/
b100001 C
b110 A
1#
#325000
0#
#330000
0*
1)
0/
1-
b100 A
b100010 C
1#
#335000
0#
#340000
1*
1/
1:
b100011 C
b1 A
1#
#345000
0#
#350000
b110110 ;
0*
0)
0/
0-
0:
b11 A
b100100 C
1#
#355000
0#
#360000
1*
1/
b100101 C
b110 A
1#
#365000
0#
#370000
0*
1)
0/
1-
b100 A
b100110 C
1#
#375000
0#
#380000
1*
1/
1:
b100111 C
b1 A
1#
#385000
0#
#390000
b110101 ;
0*
0)
0/
0-
0:
b11 A
b101000 C
1#
#395000
0#
#400000
1*
1/
b101001 C
b110 A
1#
#405000
0#
#410000
0*
1)
0/
1-
b100 A
b101010 C
1#
#415000
0#
#420000
1*
1/
1:
b101011 C
b1 A
1#
#425000
0#
#430000
b110100 ;
0*
0)
0/
0-
0:
b11 A
b101100 C
1#
#435000
0#
#440000
1*
1/
b101101 C
b110 A
1#
#445000
0#
#450000
0*
1)
0/
1-
b100 A
b101110 C
1#
#455000
0#
#460000
1*
1/
1:
b101111 C
b1 A
1#
#465000
0#
#470000
b110011 ;
0*
0)
0/
0-
0:
b11 A
b110000 C
1#
#475000
0#
#480000
1*
1/
b110001 C
b110 A
1#
#485000
0#
#490000
0*
1)
0/
1-
b100 A
b110010 C
1#
#495000
0#
#500000
1*
1/
1:
b110011 C
b1 A
1#
#505000
0#
#510000
b110010 ;
0*
0)
0/
0-
0:
b11 A
b110100 C
1#
#515000
0#
#520000
1*
1/
b110101 C
b110 A
1#
#525000
0#
#530000
0*
1)
0/
1-
b100 A
b110110 C
1#
#535000
0#
#540000
1*
1/
1:
b110111 C
b1 A
1#
#545000
0#
#550000
b110001 ;
0*
0)
0/
0-
0:
b11 A
b111000 C
1#
#555000
0#
#560000
1*
1/
b111001 C
b110 A
1#
#565000
0#
#570000
0*
1)
0/
1-
b100 A
b111010 C
1#
#575000
0#
#580000
1*
1/
1:
b111011 C
b1 A
1#
#585000
0#
#590000
b110000 ;
0*
0)
0/
0-
0:
b11 A
b111100 C
1#
#595000
0#
#600000
1*
1/
b111101 C
b110 A
1#
#605000
0#
#610000
0*
1)
0/
1-
b100 A
b111110 C
1#
#615000
0#
#620000
1*
1/
1:
b111111 C
b1 A
1#
#625000
0#
#630000
b101111 ;
0*
0)
0/
0-
0:
b11 A
b1000000 C
1#
#635000
0#
#640000
1*
1/
b1000001 C
b110 A
1#
#645000
0#
#650000
0*
1)
0/
1-
b100 A
b1000010 C
1#
#655000
0#
#660000
1*
1/
1:
b1000011 C
b1 A
1#
#665000
0#
#670000
b101110 ;
0*
0)
0/
0-
0:
b11 A
b1000100 C
1#
#675000
0#
#680000
1*
1/
b1000101 C
b110 A
1#
#685000
0#
#690000
0*
1)
0/
1-
b100 A
b1000110 C
1#
#695000
0#
#700000
1*
1/
1:
b1000111 C
b1 A
1#
#705000
0#
#710000
b101101 ;
0*
0)
0/
0-
0:
b11 A
b1001000 C
1#
#715000
0#
#720000
1*
1/
b1001001 C
b110 A
1#
#725000
0#
#730000
0*
1)
0/
1-
b100 A
b1001010 C
1#
#735000
0#
#740000
1*
1/
1:
b1001011 C
b1 A
1#
#745000
0#
#750000
b101100 ;
0*
0)
0/
0-
0:
b11 A
b1001100 C
1#
#755000
0#
#760000
1*
1/
b1001101 C
b110 A
1#
#765000
0#
#770000
0*
1)
0/
1-
b100 A
b1001110 C
1#
#775000
0#
#780000
1*
1/
1:
b1001111 C
b1 A
1#
#785000
0#
#790000
b101011 ;
0*
0)
0/
0-
0:
b11 A
b1010000 C
1#
#795000
0#
#800000
1*
1/
b1010001 C
b110 A
1#
#805000
0#
#810000
0*
1)
0/
1-
b100 A
b1010010 C
1#
#815000
0#
#820000
1*
1/
1:
b1010011 C
b1 A
1#
#825000
0#
#830000
b101010 ;
0*
0)
0/
0-
0:
b11 A
b1010100 C
1#
#835000
0#
#840000
1*
1/
b1010101 C
b110 A
1#
#845000
0#
#850000
0*
1)
0/
1-
b100 A
b1010110 C
1#
#855000
0#
#860000
1*
1/
1:
b1010111 C
b1 A
1#
#865000
0#
#870000
b101001 ;
0*
0)
0/
0-
0:
b11 A
b1011000 C
1#
#875000
0#
#880000
1*
1/
b1011001 C
b110 A
1#
#885000
0#
#890000
0*
1)
0/
1-
b100 A
b1011010 C
1#
#895000
0#
#900000
1*
1/
1:
b1011011 C
b1 A
1#
#905000
0#
#910000
b101000 ;
0*
0)
0/
0-
0:
b11 A
b1011100 C
1#
#915000
0#
#920000
1*
1/
b1011101 C
b110 A
1#
#925000
0#
#930000
0*
1)
0/
1-
b100 A
b1011110 C
1#
#935000
0#
#940000
1*
1/
1:
b1011111 C
b1 A
1#
#945000
0#
#950000
b100111 ;
0*
0)
0/
0-
0:
b11 A
b1100000 C
1#
#955000
0#
#960000
1*
1/
b1100001 C
b110 A
1#
#965000
0#
#970000
0*
1)
0/
1-
b100 A
b1100010 C
1#
#975000
0#
#980000
1*
1/
1:
b1100011 C
b1 A
1#
#985000
0#
#990000
b100110 ;
0*
0)
0/
0-
0:
b11 A
b1100100 C
1#
#995000
0#
#1000000
1*
1/
b1100101 C
b110 A
1#
#1005000
0#
#1010000
0*
1)
0/
1-
b100 A
b1100110 C
1#
#1015000
0#
#1020000
1*
1/
1:
b1100111 C
b1 A
1#
#1025000
0#
#1030000
b100101 ;
0*
0)
0/
0-
0:
b11 A
b1101000 C
1#
#1035000
0#
#1040000
1*
1/
b1101001 C
b110 A
1#
#1045000
0#
#1050000
0*
1)
0/
1-
b100 A
b1101010 C
1#
#1055000
0#
#1060000
1*
1/
1:
b1101011 C
b1 A
1#
#1065000
0#
#1070000
b100100 ;
0*
0)
0/
0-
0:
b11 A
b1101100 C
1#
#1075000
0#
#1080000
1*
1/
b1101101 C
b110 A
1#
#1085000
0#
#1090000
0*
1)
0/
1-
b100 A
b1101110 C
1#
#1095000
0#
#1100000
1*
1/
1:
b1101111 C
b1 A
1#
#1105000
0#
#1110000
b100011 ;
0*
0)
0/
0-
0:
b11 A
b1110000 C
1#
#1115000
0#
#1120000
1*
1/
b1110001 C
b110 A
1#
#1125000
0#
#1130000
0*
1)
0/
1-
b100 A
b1110010 C
1#
#1135000
0#
#1140000
1*
1/
1:
b1110011 C
b1 A
1#
#1145000
0#
#1150000
b100010 ;
0*
0)
0/
0-
0:
b11 A
b1110100 C
1#
#1155000
0#
#1160000
1*
1/
b1110101 C
b110 A
1#
#1165000
0#
#1170000
0*
1)
0/
1-
b100 A
b1110110 C
1#
#1175000
0#
#1180000
1*
1/
1:
b1110111 C
b1 A
1#
#1185000
0#
#1190000
b100001 ;
0*
0)
0/
0-
0:
b11 A
b1111000 C
1#
#1195000
0#
#1200000
1*
1/
b1111001 C
b110 A
1#
#1205000
0#
#1210000
0*
1)
0/
1-
b100 A
b1111010 C
1#
#1215000
0#
#1220000
1*
1/
1:
b1111011 C
b1 A
1#
#1225000
0#
#1230000
b100000 ;
0*
0)
0/
0-
0:
b11 A
b1111100 C
1#
#1235000
0#
#1240000
1*
1/
b1111101 C
b110 A
1#
#1245000
0#
#1250000
0*
1)
0/
1-
b100 A
b1111110 C
1#
#1255000
0#
#1260000
1*
1/
1:
b1111111 C
b1 A
1#
#1265000
0#
#1270000
b111111 ;
0*
1+
0)
0/
10
0-
0:
b11 A
b10000000 C
1#
#1275000
0#
#1280000
1*
1/
b10000001 C
1H
b1 I
b110 A
1#
#1285000
0#
#1290000
0*
1)
0/
1-
b100 A
b11 I
b10000010 C
1#
#1295000
0#
#1300000
1*
1/
1:
b10000011 C
b1 >
b1 A
1#
#1305000
0#
#1310000
b111110 ;
0*
0)
0/
0-
0:
b11 >
b11 A
b10000100 C
1#
#1315000
0#
#1320000
1*
1/
b10000101 C
b111 >
b110 A
b1 ,
b1 5
b1 B
1#
#1325000
0#
#1330000
b11 "
b11 4
0*
1)
0/
1-
b100 A
b10000110 C
1#
#1335000
0#
#1340000
1*
1/
1:
b10000111 C
b1 A
b0 ,
b0 5
b0 B
1#
#1345000
0#
#1350000
b0 "
b0 4
b111101 ;
0*
0)
0/
0-
0:
b11 A
b10001000 C
1#
#1355000
0#
#1360000
1*
1/
b10001001 C
b110 A
1#
#1365000
0#
#1370000
0*
1)
0/
1-
b100 A
b10001010 C
1#
#1375000
0#
#1380000
1*
1/
1:
b10001011 C
b1 A
1#
#1385000
0#
#1390000
b111100 ;
0*
0)
0/
0-
0:
b11 A
b10001100 C
1#
#1395000
0#
#1400000
1*
1/
b10001101 C
b110 A
1#
#1405000
0#
#1410000
0*
1)
0/
1-
b100 A
b10001110 C
1#
#1415000
0#
#1420000
1*
1/
1:
b10001111 C
b1 A
1#
#1425000
0#
#1430000
b111011 ;
0*
0)
0/
0-
0:
b11 A
b10010000 C
1#
#1435000
0#
#1440000
1*
1/
b10010001 C
b110 A
1#
#1445000
0#
#1450000
0*
1)
0/
1-
b100 A
b10010010 C
1#
#1455000
0#
#1460000
1*
1/
1:
b10010011 C
b1 A
1#
#1465000
0#
#1470000
b111010 ;
0*
0)
0/
0-
0:
b11 A
b10010100 C
1#
#1475000
0#
#1480000
1*
1/
b10010101 C
b110 A
1#
#1485000
0#
#1490000
0*
1)
0/
1-
b100 A
b10010110 C
1#
#1495000
0#
#1500000
1*
1/
1:
b10010111 C
b1 A
1#
#1505000
0#
#1510000
b111001 ;
0*
0)
0/
0-
0:
b11 A
b10011000 C
1#
#1515000
0#
#1520000
1*
1/
b10011001 C
b110 A
1#
#1525000
0#
#1530000
0*
1)
0/
1-
b100 A
b10011010 C
1#
#1535000
0#
#1540000
1*
1/
1:
b10011011 C
b1 A
1#
#1545000
0#
#1550000
b111000 ;
0*
0)
0/
0-
0:
b11 A
b10011100 C
1#
#1555000
0#
#1560000
1*
1/
b10011101 C
b110 A
1#
#1565000
0#
#1570000
0*
1)
0/
1-
b100 A
b10011110 C
1#
#1575000
0#
#1580000
1*
1/
1:
b10011111 C
b1 A
1#
#1585000
0#
#1590000
b110111 ;
0*
0)
0/
0-
0:
b11 A
b10100000 C
1#
#1595000
0#
#1600000
1*
1/
b10100001 C
b110 A
1#
#1605000
0#
#1610000
0*
1)
0/
1-
b100 A
b10100010 C
1#
#1615000
0#
#1620000
1*
1/
1:
b10100011 C
b1 A
1#
#1625000
0#
#1630000
b110110 ;
0*
0)
0/
0-
0:
b11 A
b10100100 C
1#
#1635000
0#
#1640000
1*
1/
b10100101 C
b110 A
1#
#1645000
0#
#1650000
0*
1)
0/
1-
b100 A
b10100110 C
1#
#1655000
0#
#1660000
1*
1/
1:
b10100111 C
b1 A
1#
#1665000
0#
#1670000
b110101 ;
0*
0)
0/
0-
0:
b11 A
b10101000 C
1#
#1675000
0#
#1680000
1*
1/
b10101001 C
b110 A
1#
#1685000
0#
#1690000
0*
1)
0/
1-
b100 A
b10101010 C
1#
#1695000
0#
#1700000
1*
1/
1:
b10101011 C
b1 A
1#
#1705000
0#
#1710000
b110100 ;
0*
0)
0/
0-
0:
b11 A
b10101100 C
1#
#1715000
0#
#1720000
1*
1/
b10101101 C
b110 A
1#
#1725000
0#
#1730000
0*
1)
0/
1-
b100 A
b10101110 C
1#
#1735000
0#
#1740000
1*
1/
1:
b10101111 C
b1 A
1#
#1745000
0#
#1750000
b110011 ;
0*
0)
0/
0-
0:
b11 A
b10110000 C
1#
#1755000
0#
#1760000
1*
1/
b10110001 C
b110 A
1#
#1765000
0#
#1770000
0*
1)
0/
1-
b100 A
b10110010 C
1#
#1775000
0#
#1780000
1*
1/
1:
b10110011 C
b1 A
1#
#1785000
0#
#1790000
b110010 ;
0*
0)
0/
0-
0:
b11 A
b10110100 C
1#
#1795000
0#
#1800000
1*
1/
b10110101 C
b110 A
1#
#1805000
0#
#1810000
0*
1)
0/
1-
b100 A
b10110110 C
1#
#1815000
0#
#1820000
1*
1/
1:
b10110111 C
b1 A
1#
#1825000
0#
#1830000
b110001 ;
0*
0)
0/
0-
0:
b11 A
b10111000 C
1#
#1835000
0#
#1840000
1*
1/
b10111001 C
b110 A
1#
#1845000
0#
#1850000
0*
1)
0/
1-
b100 A
b10111010 C
1#
#1855000
0#
#1860000
1*
1/
1:
b10111011 C
b1 A
1#
#1865000
0#
#1870000
b110000 ;
0*
0)
0/
0-
0:
b11 A
b10111100 C
1#
#1875000
0#
#1880000
1*
1/
b10111101 C
b110 A
1#
#1885000
0#
#1890000
0*
1)
0/
1-
b100 A
b10111110 C
1#
#1895000
0#
#1900000
1*
1/
1:
b10111111 C
b1 A
1#
#1905000
0#
#1910000
b101111 ;
0*
0)
0/
0-
0:
b11 A
b11000000 C
1#
#1915000
0#
#1920000
1*
1/
b11000001 C
b110 A
1#
#1925000
0#
#1930000
0*
1)
0/
1-
b100 A
b11000010 C
1#
#1935000
0#
#1940000
1*
1/
1:
b11000011 C
b1 A
1#
#1945000
0#
#1950000
b101110 ;
0*
0)
0/
0-
0:
b11 A
b11000100 C
1#
#1955000
0#
#1960000
1*
1/
b11000101 C
b110 A
1#
#1965000
0#
#1970000
0*
1)
0/
1-
b100 A
b11000110 C
1#
#1975000
0#
#1980000
1*
1/
1:
b11000111 C
b1 A
1#
#1985000
0#
#1990000
b101101 ;
0*
0)
0/
0-
0:
b11 A
b11001000 C
1#
#1995000
0#
#2000000
1*
1/
b11001001 C
b110 A
1#
#2005000
0#
#2010000
0*
1)
0/
1-
b100 A
b11001010 C
1#
#2015000
0#
#2020000
1*
1/
1:
b11001011 C
b1 A
1#
#2025000
0#
#2030000
b101100 ;
0*
0)
0/
0-
0:
b11 A
b11001100 C
1#
#2035000
0#
#2040000
1*
1/
b11001101 C
b110 A
1#
#2045000
0#
#2050000
0*
1)
0/
1-
b100 A
b11001110 C
1#
#2055000
0#
#2060000
1*
1/
1:
b11001111 C
b1 A
1#
#2065000
0#
#2070000
b101011 ;
0*
0)
0/
0-
0:
b11 A
b11010000 C
1#
#2075000
0#
#2080000
1*
1/
b11010001 C
b110 A
1#
#2085000
0#
#2090000
0*
1)
0/
1-
b100 A
b11010010 C
1#
#2095000
0#
#2100000
1*
1/
1:
b11010011 C
b1 A
1#
#2105000
0#
#2110000
b101010 ;
0*
0)
0/
0-
0:
b11 A
b11010100 C
1#
#2115000
0#
#2120000
1*
1/
b11010101 C
b110 A
1#
#2125000
0#
#2130000
0*
1)
0/
1-
b100 A
b11010110 C
1#
#2135000
0#
#2140000
1*
1/
1:
b11010111 C
b1 A
1#
#2145000
0#
#2150000
b101001 ;
0*
0)
0/
0-
0:
b11 A
b11011000 C
1#
#2155000
0#
#2160000
1*
1/
b11011001 C
b110 A
1#
#2165000
0#
#2170000
0*
1)
0/
1-
b100 A
b11011010 C
1#
#2175000
0#
#2180000
1*
1/
1:
b11011011 C
b1 A
1#
#2185000
0#
#2190000
b101000 ;
0*
0)
0/
0-
0:
b11 A
b11011100 C
1#
#2195000
0#
#2200000
1*
1/
b11011101 C
b110 A
1#
#2205000
0#
#2210000
0*
1)
0/
1-
b100 A
b11011110 C
1#
#2215000
0#
#2220000
1*
1/
1:
b11011111 C
b1 A
1#
#2225000
0#
#2230000
b100111 ;
0*
0)
0/
0-
0:
b11 A
b11100000 C
1#
#2235000
0#
#2240000
1*
1/
b11100001 C
b110 A
1#
#2245000
0#
#2250000
0*
1)
0/
1-
b100 A
b11100010 C
1#
#2255000
0#
#2260000
1*
1/
1:
b11100011 C
b1 A
1#
#2265000
0#
#2270000
b100110 ;
0*
0)
0/
0-
0:
b11 A
b11100100 C
1#
#2275000
0#
#2280000
1*
1/
b11100101 C
b110 A
1#
#2285000
0#
#2290000
0*
1)
0/
1-
b100 A
b11100110 C
1#
#2295000
0#
#2300000
1*
1/
1:
b11100111 C
b1 A
1#
#2305000
0#
#2310000
b100101 ;
0*
0)
0/
0-
0:
b11 A
b11101000 C
1#
#2315000
0#
#2320000
1*
1/
b11101001 C
b110 A
1#
#2325000
0#
#2330000
0*
1)
0/
1-
b100 A
b11101010 C
1#
#2335000
0#
#2340000
1*
1/
1:
b11101011 C
b1 A
1#
#2345000
0#
#2350000
b100100 ;
0*
0)
0/
0-
0:
b11 A
b11101100 C
1#
#2355000
0#
#2360000
1*
1/
b11101101 C
b110 A
1#
#2365000
0#
#2370000
0*
1)
0/
1-
b100 A
b11101110 C
1#
#2375000
0#
#2380000
1*
1/
1:
b11101111 C
b1 A
1#
#2385000
0#
#2390000
b100011 ;
0*
0)
0/
0-
0:
b11 A
b11110000 C
1#
#2395000
0#
#2400000
1*
1/
b11110001 C
b110 A
1#
#2405000
0#
#2410000
0*
1)
0/
1-
b100 A
b11110010 C
1#
#2415000
0#
#2420000
1*
1/
1:
b11110011 C
b1 A
1#
#2425000
0#
#2430000
b100010 ;
0*
0)
0/
0-
0:
b11 A
b11110100 C
1#
#2435000
0#
#2440000
1*
1/
b11110101 C
b110 A
1#
#2445000
0#
#2450000
0*
1)
0/
1-
b100 A
b11110110 C
1#
#2455000
0#
